<?xml version="1.0" encoding="utf-8" ?><dwsync><file name=".DS_Store" server="74.208.174.95" local="3536137954" remote="12126083672" Dst="-1" /><file name="animation.png" server="74.208.174.95" local="3536137954" remote="12126083672" Dst="-1" /><file name="application.png" server="74.208.174.95" local="3536137954" remote="12126083672" Dst="-1" /><file name="animation-bg.jpg" server="74.208.174.95" local="3536137954" remote="12126083672" Dst="-1" /><file name="architects.png" server="74.208.174.95" local="3536137954" remote="12126083672" Dst="-1" /><file name="animation.svg" server="74.208.174.95" local="3536137954" remote="12126083672" Dst="-1" /><file name="attorneys.png" server="74.208.174.95" local="3536137954" remote="12126083672" Dst="-1" /><file name="city_building.svg" server="74.208.174.95" local="3536137954" remote="12126083672" Dst="-1" /><file name="close-button.png" server="74.208.174.95" local="3536137954" remote="12126083672" Dst="-1" /><file name="construction-manager-as-advisor.jpg" server="74.208.174.95" local="3536137954" remote="12126083732" Dst="-1" /><file name="architects.svg" server="74.208.174.95" local="3536137954" remote="12126083672" Dst="-1" /><file name="construction-manager-as-contractor.jpg" server="74.208.174.95" local="3536137954" remote="12126083732" Dst="-1" /><file name="continuation-sheet.png" server="74.208.174.95" local="3536137954" remote="12126083732" Dst="-1" /><file name="contract-for-construction.png" server="74.208.174.95" local="3536137954" remote="12126083732" Dst="-1" /><file name="attorneys.svg" server="74.208.174.95" local="3536137954" remote="12126083732" Dst="-1" /><file name="contractor-subcontractor.png" server="74.208.174.95" local="3536137954" remote="12126083732" Dst="-1" /><file name="contractor.png" server="74.208.174.95" local="3536137954" remote="12126083732" Dst="-1" /><file name="contractors.png" server="74.208.174.95" local="3536137954" remote="12126083732" Dst="-1" /><file name="design-bid-build.jpg" server="74.208.174.95" local="3536137954" remote="12126083732" Dst="-1" /><file name="design-build.jpg" server="74.208.174.95" local="3536137954" remote="12126083732" Dst="-1" /><file name="endLogo.png" server="74.208.174.95" local="3536137954" remote="12126083732" Dst="-1" /><file name="footer-products.png" server="74.208.174.95" local="3536137954" remote="12126083732" Dst="-1" /><file name="footer-tools.png" server="74.208.174.95" local="3536137954" remote="12126083732" Dst="-1" /><file name="history-dot.svg" server="74.208.174.95" local="3536137954" remote="12126083732" Dst="-1" /><file name="contractors.svg" server="74.208.174.95" local="3536137954" remote="12126083732" Dst="-1" /><file name="history.svg" server="74.208.174.95" local="3536137954" remote="12126083732" Dst="-1" /><file name="home-button.svg" server="74.208.174.95" local="3536137954" remote="12126083732" Dst="-1" /><file name="footer-bg.jpg" server="74.208.174.95" local="3536137954" remote="12126083732" Dst="-1" /><file name="home-dot.svg" server="74.208.174.95" local="3536137954" remote="12126083732" Dst="-1" /><file name="integrated-project-delivery.jpg" server="74.208.174.95" local="3536137954" remote="12126083732" Dst="-1" /><file name="logo.png" server="74.208.174.95" local="3536137954" remote="12126083732" Dst="-1" /><file name="logo.svg" server="74.208.174.95" local="3536137954" remote="12126083732" Dst="-1" /><file name="owners.png" server="74.208.174.95" local="3536137954" remote="12126083732" Dst="-1" /><file name="other-project-types.jpg" server="74.208.174.95" local="3536137954" remote="12126083732" Dst="-1" /><file name="second-bg.png" server="74.208.174.95" local="3536137954" remote="12126083732" Dst="-1" /><file name="second-bg.svg" server="74.208.174.95" local="3536137954" remote="12126083732" Dst="-1" /><file name="second.svg" server="74.208.174.95" local="3536137954" remote="12126083732" Dst="-1" /><file name="standard-owner.png" server="74.208.174.95" local="3536137954" remote="12126083732" Dst="-1" /><file name="top-02.png" server="74.208.174.95" local="3536137954" remote="12126083732" Dst="-1" /><file name="second-bg--white-blots.svg" server="74.208.174.95" local="3536137954" remote="12126083732" Dst="-1" /><file name="top.png" server="74.208.174.95" local="3536137954" remote="12126083732" Dst="-1" /><file name="owners.svg" server="74.208.174.95" local="3536137954" remote="12126083732" Dst="-1" /><file name="who-uses-bg.jpg" server="74.208.174.95" local="3536137954" remote="12126083732" Dst="-1" /><file name="Untitled-2.jpg" server="74.208.174.95" local="3536137954" remote="12126083732" Dst="-1" /><file name="who-uses-bg.png" server="74.208.174.95" local="3536137954" remote="12126083732" Dst="-1" /><file name="who-uses-bg.svg" server="74.208.174.95" local="3536137954" remote="12126083732" Dst="-1" /></dwsync>